biriscv/src/core/not used/old_error_detector/error_detector.v
module error_detector (output error, input data, clk);
    reg q;

    always @(posedge clk) begin
        q <= data;
    end 

    assign error = data ^ q;
endmodule

src/transition_detector.v
module transition_detector 
    #(parameter DATA_WIDTH = 1) (
        input clk, reset,
        input [DATA_WIDTH-1:0] data,
        output reg [DATA_WIDTH-1:0] transition
    );

    wire [DATA_WIDTH-1:0] and_out;
    wire [DATA_WIDTH-1:0] buf_out;
    wire [DATA_WIDTH-1:0] nor_out;
    wire [DATA_WIDTH-1:0] xor_out;

    assign and_out = data & 1;
    assign buf_out = and_out;
    assign nor_out = ~(buf_out | 1);
    assign xor_out = data ^ nor_out;

    always @(posedge xor_out) begin
        if (reset==1'b1)
            transition <= 1'b0;
        else
            transition <= clk;
    end




endmodule

src/final_error_detector.v
module final_error_detector
    # (parameter DATA_WIDTH = 1) (
        input clk, reset,
        input [DATA_WIDTH-1:0] data,
        output error
    );

    wire transition, initial_error;

    transition_detector TD(.clk(clk), .reset(reset), .data(data), .transition(transition));
    error_detector ED(.error(initial_error), .data(data), .clk(clk));

    assign error = initial_error & transition;
endmodule

src/final_error_detector_tb.v
module final_error_detector_tb;
    reg data;
    reg clk;
    reg reset;
    wire error;
    wire transition;

final_error_detector final_ED (.clk(clk), .reset(reset), .data(data), .error(error));

initial begin
    clk = 1;
    data = 0;
    #70
    $finish;
end

always begin
    #5 clk = ~clk;
end

always begin
    #7 data = ~data;
end

initial begin
   $dumpfile("final_ED.vcd");
   $dumpvars(0, final_error_detector_tb);
 end

endmodule

src/final_ED.vcd
$date
	Wed Nov  8 15:49:17 2023
$end
$version
	Icarus Verilog
$end
$timescale
	1s
$end
$scope module final_error_detector_tb $end
$var wire 1 ! error $end
$var reg 1 " clk $end
$var reg 1 # data $end
$var reg 1 $ reset $end
$scope module final_ED $end
$var wire 1 " clk $end
$var wire 1 # data $end
$var wire 1 ! error $end
$var wire 1 $ reset $end
$var wire 1 % transition $end
$var wire 1 & initial_error $end
$var parameter 32 ' DATA_WIDTH $end
$scope module ED $end
$var wire 1 " clk $end
$var wire 1 # data $end
$var wire 1 & error $end
$var reg 1 ( q $end
$upscope $end
$scope module TD $end
$var wire 1 ) buf_out $end
$var wire 1 " clk $end
$var wire 1 # data $end
$var wire 1 $ reset $end
$var wire 1 * xor_out $end
$var wire 1 + nor_out $end
$var wire 1 , and_out $end
$var parameter 32 - DATA_WIDTH $end
$var reg 1 % transition $end
$upscope $end
$upscope $end
$upscope $end
$enddefinitions $end
$comment Show the parameter values. $end
$dumpall
b1 -
b1 '
$end
#0
$dumpvars
0,
0+
0*
0)
0(
0&
x%
x$
0#
1"
0!
$end
#5
0"
#7
0%
0!
1)
1,
1&
1*
1#
#10
0&
1(
1"
#14
0)
0,
1&
0*
0#
#15
0"
#20
0&
0(
1"
#21
1!
1%
1)
1,
1&
1*
1#
#25
0"
#28
0!
0)
0,
0&
0*
0#
#30
1"
#35
0%
0!
1)
1,
1&
1*
0"
1#
#40
0&
1(
1"
#42
0)
0,
1&
0*
0#
#45
0"
#49
1)
1,
0&
1*
1#
#50
1"
#55
0"
#56
0)
0,
1&
0*
0#
#60
0&
0(
1"
#63
1!
1%
1)
1,
1&
1*
1#
#65
0"
#70
0!
0)
0,
0&
0*
1"
0#
